tunic-1.3.0.dist-info/METADATA
tunic-1.3.0.dist-info/RECORD
tunic-1.3.0.dist-info/WHEEL
tunic-1.3.0.dist-info/metadata.json
tunic-1.3.0.dist-info/DESCRIPTION.rst
tunic-1.3.0.dist-info/zip-safe
tunic-1.3.0.dist-info/top_level.txt
tunic/__init__.py
tunic/api.py
tunic/core.py
tunic/install.py
