Metadata-Version: 2.0
Name: tunic
Version: 1.3.0
Summary: Deployment related Fabric utilities
Home-page: https://github.com/tshlabs/tunic
Author: TSH Labs
Author-email: projects@tshlabs.org
License: MIT
Platform: UNKNOWN
Classifier: Development Status :: 5 - Production/Stable
Classifier: License :: OSI Approved :: MIT License
Classifier: Operating System :: POSIX
Classifier: Programming Language :: Python
Classifier: Programming Language :: Python :: 2.6
Classifier: Programming Language :: Python :: 2.7
Classifier: Topic :: System :: Installation/Setup
Requires-Dist: fabric
